c6/__init__.py
c6/cell.py
c6/plot.py
c6/space.py
c6/data/__init__.py
c6/utils/__init__.py
c6/utils/encoding.py
c6/utils/math.py
c6/utils/nameing.py
c6/utils/serialize.py
c6-0.4.0.dist-info/LICENSE
c6-0.4.0.dist-info/METADATA
c6-0.4.0.dist-info/WHEEL
c6-0.4.0.dist-info/entry_points.txt
c6-0.4.0.dist-info/top_level.txt
c6-0.4.0.dist-info/RECORD
